fastapi_stoplight.py
fastapi_stoplight-0.1.0.dist-info/METADATA
fastapi_stoplight-0.1.0.dist-info/WHEEL
fastapi_stoplight-0.1.0.dist-info/licenses/LICENSE
fastapi_stoplight-0.1.0.dist-info/RECORD
