Metadata-Version: 2.4
Name: fastapi-stoplight
Version: 0.1.0
Summary: 一个将 FastAPI 与 Stoplight Elements 结合的库，用于快速生成美观、交互式的 API 文档
Project-URL: Homepage, https://github.com/yourusername/fastapi-stoplight
Project-URL: Documentation, https://github.com/yourusername/fastapi-stoplight#readme
Project-URL: Repository, https://github.com/yourusername/fastapi-stoplight.git
Project-URL: Bug Tracker, https://github.com/yourusername/fastapi-stoplight/issues
Project-URL: Changelog, https://github.com/yourusername/fastapi-stoplight/blob/main/CHANGELOG.md
Author: 月间
Maintainer: 月间
License-Expression: MIT
License-File: LICENSE
Keywords: api,documentation,elements,fastapi,openapi,stoplight,swagger
Classifier: Development Status :: 4 - Beta
Classifier: Framework :: FastAPI
Classifier: Intended Audience :: Developers
Classifier: License :: OSI Approved :: MIT License
Classifier: Programming Language :: Python :: 3
Classifier: Programming Language :: Python :: 3.8
Classifier: Programming Language :: Python :: 3.9
Classifier: Programming Language :: Python :: 3.10
Classifier: Programming Language :: Python :: 3.11
Classifier: Programming Language :: Python :: 3.12
Classifier: Topic :: Internet :: WWW/HTTP :: Dynamic Content
Classifier: Topic :: Software Development :: Documentation
Classifier: Topic :: Software Development :: Libraries :: Python Modules
Requires-Python: >=3.8
Requires-Dist: fastapi>=0.68.0
Provides-Extra: dev
Requires-Dist: httpx>=0.23.0; extra == 'dev'
Requires-Dist: pytest-asyncio>=0.19.0; extra == 'dev'
Requires-Dist: pytest>=6.0.0; extra == 'dev'
Requires-Dist: uvicorn>=0.15.0; extra == 'dev'
